cowin/__init__.py
cowin/api.py
cowin/base_api.py
cowin/constants.py
cowin/utils.py
cowin_vaccine_api-0.0.3.dist-info/METADATA
cowin_vaccine_api-0.0.3.dist-info/WHEEL
cowin_vaccine_api-0.0.3.dist-info/entry_points.txt
cowin_vaccine_api-0.0.3.dist-info/top_level.txt
cowin_vaccine_api-0.0.3.dist-info/RECORD
