Metadata-Version: 2.1
Name: cowin-vaccine-api
Version: 0.0.3
Summary: API wrapper for Cowin Api
Home-page: https://github.com/its-k/cowin-api
Author: Kishore
Author-email: kishore4110@gmail.com
License: MIT
Platform: UNKNOWN
Classifier: License :: OSI Approved :: MIT License
Classifier: Programming Language :: Python :: 3.6
Classifier: Programming Language :: Python :: 3.7
Classifier: Programming Language :: Python :: 3.8
Requires-Dist: datetime
Requires-Dist: fake-useragent
Requires-Dist: requests
